umd_api/__init__.py
umd_api/general/__init__.py
umd_api/general/base_api.py
umd_api/general/bus.py
umd_api/general/courses.py
umd_api/general/majors.py
umd_api/general/map.py
umd_api/general/professors.py
umd_api/planet_terp/__init__.py
umd_api/planet_terp/base_api.py
umd_api/planet_terp/courses.py
umd_api/planet_terp/grades.py
umd_api/planet_terp/professors.py
umd_api/planet_terp/search.py
umd_api/weather/__init__.py
umd_api/weather/forecast.py
umd_api/weather/weather.py
umd_api-0.65.86.dist-info/LICENSE
umd_api-0.65.86.dist-info/METADATA
umd_api-0.65.86.dist-info/WHEEL
umd_api-0.65.86.dist-info/top_level.txt
umd_api-0.65.86.dist-info/RECORD
