Metadata-Version: 2.2
Name: umd-api
Version: 0.65.86
Summary: A package for accessing the UMD API in Python
Author-email: Eshan Iyer <eshaniyer@duck.com>
License: MIT
Project-URL: Documentation, https://github.com/Nazchanel/umd-api-python/blob/master/README.md
Project-URL: Source, https://github.com/Nazchanel/umd-api-python
Keywords: umd,education,API
Requires-Python: >=3.10
License-File: LICENSE
Requires-Dist: requests<3.0,>=2.31.0
Requires-Dist: beautifulsoup4<5.0,>=4.12.2
Requires-Dist: regex<2025.0,>=2024.10.30
Requires-Dist: pytz<2024.0,>=2023.3
Requires-Dist: pandas<3.0,>=2.0.3
